jsonschema2md2/__init__.py
jsonschema2md2/locales/README.md
jsonschema2md2/locales/fr/LC_MESSAGES/messages.po
jsonschema2md2/locales/fr_CH/LC_MESSAGES/messages.po
jsonschema2md2/locales/pt/LC_MESSAGES/messages.po
jsonschema2md2/locales/pt_BR/LC_MESSAGES/messages.po
jsonschema2md2-1.7.0.dist-info/LICENSE
jsonschema2md2-1.7.0.dist-info/METADATA
jsonschema2md2-1.7.0.dist-info/WHEEL
jsonschema2md2-1.7.0.dist-info/entry_points.txt
jsonschema2md2-1.7.0.dist-info/RECORD
