Metadata-Version: 2.3
Name: jsonschema2md2
Version: 1.7.0
Summary: Convert JSON Schema to human-readable Markdown documentation
License: Apache-2.0
Keywords: JSON Schema,Markdown,Converter,Parser,Documentation
Author: Ralf Gabriels
Author-email: ralfg@hotmail.be
Maintainer: Stéphane Brunner
Maintainer-email: stephane.brunner@gmail.com
Requires-Python: >=3.9
Classifier: Development Status :: 4 - Beta
Classifier: Intended Audience :: Developers
Classifier: Operating System :: OS Independent
Classifier: Programming Language :: Python
Classifier: Programming Language :: Python :: 3
Classifier: Programming Language :: Python :: 3.9
Classifier: Programming Language :: Python :: 3.10
Classifier: Programming Language :: Python :: 3.11
Classifier: Programming Language :: Python :: 3.12
Classifier: Programming Language :: Python :: 3.13
Classifier: Topic :: Documentation
Classifier: Topic :: Software Development :: Documentation
Requires-Dist: PyYAML (>=6,<7)
Requires-Dist: babel (>=2,<3)
Requires-Dist: markdown (>=3,<4)
Project-URL: Bug Tracker, https://github.com/sbrunner/jsonschema2md/issues
Project-URL: Repository, https://github.com/sbrunner/jsonschema2md
